{
  "name": "Eunice Garcia",
  "age": 43,
  "address": {
    "street": "Kufepe Turnpike",
    "city": "Caomuha",
    "state": "NY",
    "zip": "35092"
  },
  "contact": {
    "phone": "(231) 884-6137",
    "servicePhone": "800822832"
  },
  "birthday": "1984-04-20T08:31:28.785Z",
  "ip": "10.199.69.231",
  "foo": "bar",
  "profile": {
    "about": "Ve odomih nipbertu fopuffow zepowe korcugeg hifbig midwi jemok lozpi ni olsujruc tubajilo zolrog gateaso het uhlooke. Wevu wopu nigodekel malefah bevcispe jeve cahahivo ga ado bi joscivtoc nogmehe. Je sulwe sa dunpocig iv la cucese hej tin zadgupa vomgah duc car olojas gotse.",
    "bio": "Lojgujen obvo gugi gafu mupani duvos hadbavam albin ridec ifvob kit jo jonrici mitdomte vahdezem vusifo. Mujahfa ca zakket saj dom jesuceki utukaw vo bel vig vem ni ho fimatik ifepazeh segewik rojotniz. Zu waam japevile duh cog osidi ta livez tujucig soededo ce runove."
  },
  "apiKey": "749b5e422b2d215eac0641457af17a5435208eebbe65c29681bca079831adafd",
  "currency": {
    "code": "KES",
    "name": "Kenya Shilling"
  }
}