{
  "name": "Jennie Casey",
  "age": 32,
  "address": {
    "street": "Bedod River",
    "city": "Sietofat",
    "state": "GA",
    "zip": "07278"
  },
  "contact": {
    "phone": "(201) 242-1566",
    "servicePhone": "800225684"
  },
  "birthday": "1960-05-17T05:16:10.517Z",
  "ip": "139.213.163.52",
  "foo": "bar",
  "profile": {
    "about": "Mioliij human hilwew soma kaewenag in katet li zepjogi miko al wovluswi gaz orejusdej oreogu. Sipuje butuw cez patovo ginkahik cos ziwrajaf savhud iwhobjim movazgum nep kufauc be zala. Tipuj pegheki mit levvag uravoesu paawehu caw kegew co ome miso li oc. Ih kur bi leswitahu vud pedi beze caj ucjecbi suasawap evaehfa pih zi re pepe hu. Wanawiv sa nagov dibow efmaj gasnukec ga ve bipe li katne gokpol. Cag ahafi dov ozgud ivatosoc silap jamurbur nopja abo wir ofhecfun ma jeple.",
    "bio": "Oruvi obeuhi ruvezmov kada ce enake ciwudfok nizus ko pek va ta bedjoba mul hotuk. Utreru hipsub kewtelkeh zejigoas gavoho nawoseze runhi gic if mok jaggotok urisavib kotob mumfac azu toficfo. Wolrobdif nip za upzewen rerugcad pubisbul je jitpo downad hovbufo hotu duwgo. Ufuomagiw ja olopa fobobca kulefmol rettocaz ecnudvu kaga teraebu legconbiz feal waozafid zoc efe. Ushasca lousmas cutebluf hinziri jiklin mevviluf fagusube mauk iroicu vasabi kizga nib bis giccuhvah mu oga kigwid. Hewpos cocomta woika mir zobini bizni dehig vekipci ebu uz hef zu to paruzzi kiafehow."
  },
  "apiKey": "21b5ea19f66295dd406585b7e35c57a6eb73aa570960049a499fbda3ad717a19",
  "currency": {
    "code": "BAM",
    "name": "Bosnia and Herzegovina Convertible Marka"
  }
}